polypacket/__init__.py
polypacket/poly_make.py
polypacket/polypacket_cli.py
polypacket/polyservice.py
polypacket/protocol.py
polypacket/examples/example.py
polypacket/examples/sample_protocol.xml
polypacket/examples/sample_protocol.yml
polypacket/plugins/ota.yml
polypacket/templates/app_template.c
polypacket/templates/app_template.h
polypacket/templates/c_header_template.h
polypacket/templates/c_source_template.c
polypacket/templates/cmake_template.txt
polypacket/templates/cpp_header_template.h
polypacket/templates/cpp_source_template.cpp
polypacket/templates/cpp_subclass_template.cpp
polypacket/templates/cpp_subclass_template.h
polypacket/templates/doc_template.html
polypacket/templates/doc_template.md
polypacket/templates/doc_template.rst
polypacket/templates/javascript_template.js
polypacket/templates/python_template.py
polypacket/templates/readme_template.md
polypacket/templates/util_main_adv_template.c
polypacket/templates/util_main_template.c
polypacket/transport/SerialTransport.py
polypacket/transport/TcpTransport.py
polypacket/transport/Transport.py
polypacket/transport/UdpTransport.py
polypacket/transport/WebsocketTransport.py
polypacket/transport/__init__.py
polypacket-1.1.42.dist-info/METADATA
polypacket-1.1.42.dist-info/WHEEL
polypacket-1.1.42.dist-info/entry_points.txt
polypacket-1.1.42.dist-info/licenses/LICENSE.txt
polypacket-1.1.42.dist-info/RECORD
