Metadata-Version: 2.4
Name: polypacket
Version: 1.1.42
Summary: A tool for building protocol services
Project-URL: Documentation, https://mrt.readthedocs.io/en/latest/pages/polypacket/polypacket.html
Author-email: Jason Berger <Berge472@gmail.com>
License: MIT
License-File: LICENSE.txt
Classifier: License :: OSI Approved :: MIT License
Classifier: Operating System :: OS Independent
Classifier: Programming Language :: Python :: 3
Requires-Python: >=3.0
Requires-Dist: cobs
Requires-Dist: mako
Requires-Dist: markdown
Requires-Dist: mrtutils
Requires-Dist: prompt-toolkit
Requires-Dist: pyserial
Requires-Dist: pyyaml
Requires-Dist: urllib3
Requires-Dist: validators
Requires-Dist: websocket-client
Requires-Dist: websockets
